salish/__init__.py
salish-0.1.0.dist-info/METADATA
salish-0.1.0.dist-info/WHEEL
salish-0.1.0.dist-info/RECORD
