Metadata-Version: 2.1
Name: salish
Version: 0.1.0
Summary: 
Author: Ben Skubi
Author-email: bskubi@gmail.com
Requires-Python: >=3.10,<4.0
Classifier: Programming Language :: Python :: 3
Classifier: Programming Language :: Python :: 3.10
Classifier: Programming Language :: Python :: 3.11
Classifier: Programming Language :: Python :: 3.12
